pyvrp_shipment/__init__.py
pyvrp_shipment/py.typed
pyvrp_shipment-0.2.2.dist-info/METADATA
pyvrp_shipment-0.2.2.dist-info/WHEEL
pyvrp_shipment-0.2.2.dist-info/licenses/LICENSE
pyvrp_shipment-0.2.2.dist-info/RECORD
