Metadata-Version: 2.4
Name: pyvrp-shipment
Version: 0.2.2
Summary: `pyvrp-shipment` is a package for wrapper for solving shipment in PyVRP
Project-URL: homepage, https://github.com/SaitoTsutomu/pyvrp-shipment
Author-email: Saito Tsutomu <tsutomu7@hotmail.co.jp>
License: Apache-2.0
License-File: LICENSE
Classifier: Development Status :: 1 - Planning
Classifier: License :: OSI Approved :: Apache Software License
Classifier: Programming Language :: Python
Classifier: Topic :: Scientific/Engineering
Classifier: Topic :: Software Development
Requires-Python: >=3.12
Requires-Dist: pyvrp==0.9.1
